{
  "openapi": "3.0.1",
  "info": {
    "title": "cv site",
    "version": "1.0"
  },
  "paths": {
    "/api/GitHub/portfolio": {
      "get": {
        "tags": [
          "GitHub"
        ],
        "parameters": [
          {
            "name": "userName",
            "in": "query",
            "schema": {
              "type": "string"
            }
          }
        ],
        "responses": {
          "200": {
            "description": "OK"
          }
        }
      }
    },
    "/api/GitHub/search": {
      "get": {
        "tags": [
          "GitHub"
        ],
        "parameters": [
          {
            "name": "repoName",
            "in": "query",
            "schema": {
              "type": "string",
              "default": ""
            }
          },
          {
            "name": "language",
            "in": "query",
            "schema": {
              "type": "string",
              "default": ""
            }
          },
          {
            "name": "userName",
            "in": "query",
            "schema": {
              "type": "string",
              "default": ""
            }
          }
        ],
        "responses": {
          "200": {
            "description": "OK"
          }
        }
      }
    }
  },
  "components": { }
}